setup.py
snake_game_idrys01/__init__.py
snake_game_idrys01/board.py
snake_game_idrys01/food.py
snake_game_idrys01/snake.py
snake_game_idrys01/snake_game.py
snake_game_idrys01/utility.py
snake_game_idrys01.egg-info/PKG-INFO
snake_game_idrys01.egg-info/SOURCES.txt
snake_game_idrys01.egg-info/dependency_links.txt
snake_game_idrys01.egg-info/entry_points.txt
snake_game_idrys01.egg-info/requires.txt
snake_game_idrys01.egg-info/top_level.txt