Metadata-Version: 2.1
Name: snake-game-idrys01
Version: 0.203
Requires-Dist: tk
